dinogame/__init__.py
dinogame/__main__.py
dinogame/version.py
dinogame/assets/cactus.png
dinogame/assets/cloud.png
dinogame/assets/flyer.png
dinogame/assets/ground.png
dinogame/assets/player.png
dinogame/callback/__init__.py
dinogame/game/__init__.py
dinogame/game/game.py
dinogame/game/entities/__init__.py
dinogame/game/entities/decorations.py
dinogame/game/entities/ground.py
dinogame/game/entities/moving_object.py
dinogame/game/entities/obstacles.py
dinogame/game/entities/player.py
dinogame/tictoc/__init__.py
dino_game-0.3.dist-info/LICENSE
dino_game-0.3.dist-info/METADATA
dino_game-0.3.dist-info/WHEEL
dino_game-0.3.dist-info/top_level.txt
dino_game-0.3.dist-info/RECORD
