Metadata-Version: 2.1
Name: dino-game
Version: 0.3
Summary: A Python reimplementation of the famous dino game, thought for autonomous control
Home-page: https://github.com/RobertoBochet/dino-game
Author: Roberto Bochet
Author-email: robertobochet@gmail.com
License: gpl-3.0
Keywords: game,gym,dino,pygame
Platform: UNKNOWN
Classifier: Development Status :: 4 - Beta
Classifier: Intended Audience :: Developers
Classifier: Intended Audience :: Education
Classifier: Intended Audience :: Science/Research
Classifier: Operating System :: OS Independent
Classifier: License :: OSI Approved :: GNU General Public License v3 (GPLv3)
Classifier: Programming Language :: Python :: 3
Requires-Python: >=3.6
Requires-Dist: pygame (>=2.0.0.dev6)
